spark_feature_push_client/__init__.py
spark_feature_push_client/client.py
"spark_feature_push_client/utils/__init__,py"
spark_feature_push_client/utils/helpers.py
spark_feature_push_client-1.0.1.dist-info/METADATA
spark_feature_push_client-1.0.1.dist-info/WHEEL
spark_feature_push_client-1.0.1.dist-info/RECORD
